contextgit/__init__.py
contextgit/__main__.py
contextgit/constants.py
contextgit/exceptions.py
contextgit/py.typed
contextgit/cli/__init__.py
contextgit/cli/app.py
contextgit/cli/commands.py
contextgit/cli/confirm_command.py
contextgit/cli/fmt_command.py
contextgit/cli/hooks_command.py
contextgit/cli/show_command.py
contextgit/cli/watch_command.py
contextgit/domain/__init__.py
contextgit/domain/checksum/__init__.py
contextgit/domain/checksum/calculator.py
contextgit/domain/config/__init__.py
contextgit/domain/config/manager.py
contextgit/domain/id_gen/__init__.py
contextgit/domain/id_gen/generator.py
contextgit/domain/index/__init__.py
contextgit/domain/index/manager.py
contextgit/domain/linking/__init__.py
contextgit/domain/linking/engine.py
contextgit/domain/location/__init__.py
contextgit/domain/location/markdown.py
contextgit/domain/location/resolver.py
contextgit/domain/location/snippet.py
contextgit/domain/metadata/__init__.py
contextgit/domain/metadata/parser.py
contextgit/handlers/__init__.py
contextgit/handlers/base.py
contextgit/handlers/confirm_handler.py
contextgit/handlers/extract_handler.py
contextgit/handlers/fmt_handler.py
contextgit/handlers/hooks_handler.py
contextgit/handlers/impact_handler.py
contextgit/handlers/init_handler.py
contextgit/handlers/link_handler.py
contextgit/handlers/mcp_server_handler.py
contextgit/handlers/next_id_handler.py
contextgit/handlers/relevant_handler.py
contextgit/handlers/scan_handler.py
contextgit/handlers/show_handler.py
contextgit/handlers/status_handler.py
contextgit/handlers/validate_handler.py
contextgit/handlers/watch_handler.py
contextgit/infra/__init__.py
contextgit/infra/filesystem.py
contextgit/infra/output.py
contextgit/infra/yaml_io.py
contextgit/mcp/__init__.py
contextgit/mcp/schemas.py
contextgit/mcp/server.py
contextgit/models/__init__.py
contextgit/models/config.py
contextgit/models/enums.py
contextgit/models/index.py
contextgit/models/link.py
contextgit/models/location.py
contextgit/models/node.py
contextgit-1.2.0.dist-info/licenses/LICENSE
contextgit-1.2.0.dist-info/METADATA
contextgit-1.2.0.dist-info/WHEEL
contextgit-1.2.0.dist-info/entry_points.txt
contextgit-1.2.0.dist-info/top_level.txt
contextgit-1.2.0.dist-info/RECORD
