Metadata-Version: 2.4
Name: contextgit
Version: 1.2.0
Summary: Requirements traceability for LLM-assisted software development. Track relationships from business needs through system specs, architecture, code, and tests.
Author-email: Saleh <saleh@cronlytic.com>
Maintainer-email: Saleh <saleh@cronlytic.com>
License: MIT
Project-URL: Homepage, https://github.com/Mohamedsaleh14/ContextGit
Project-URL: Documentation, https://github.com/Mohamedsaleh14/ContextGit#readme
Project-URL: Repository, https://github.com/Mohamedsaleh14/ContextGit.git
Project-URL: Issues, https://github.com/Mohamedsaleh14/ContextGit/issues
Project-URL: Changelog, https://github.com/Mohamedsaleh14/ContextGit/releases
Project-URL: Buy Me a Coffee, https://buymeacoffee.com/saleh_tawfik
Keywords: requirements,traceability,llm,ai,documentation,software-engineering,cli,markdown,yaml,claude,cursor,development-tools
Classifier: Development Status :: 5 - Production/Stable
Classifier: Environment :: Console
Classifier: Intended Audience :: Developers
Classifier: License :: OSI Approved :: MIT License
Classifier: Operating System :: OS Independent
Classifier: Programming Language :: Python :: 3
Classifier: Programming Language :: Python :: 3.11
Classifier: Programming Language :: Python :: 3.12
Classifier: Programming Language :: Python :: 3.13
Classifier: Topic :: Software Development
Classifier: Topic :: Software Development :: Documentation
Classifier: Topic :: Software Development :: Quality Assurance
Classifier: Topic :: Text Processing :: Markup :: Markdown
Classifier: Typing :: Typed
Requires-Python: >=3.11
License-File: LICENSE
Requires-Dist: typer>=0.9.0
Requires-Dist: rich>=13.0.0
Requires-Dist: ruamel.yaml>=0.18.0
Provides-Extra: dev
Requires-Dist: pytest>=7.4.0; extra == "dev"
Requires-Dist: pytest-cov>=4.1.0; extra == "dev"
Requires-Dist: pytest-benchmark>=4.0.0; extra == "dev"
Requires-Dist: pytest-xdist>=3.3.0; extra == "dev"
Requires-Dist: pytest-mock>=3.11.0; extra == "dev"
Requires-Dist: pytest-timeout>=2.1.0; extra == "dev"
Requires-Dist: ruff>=0.1.0; extra == "dev"
Requires-Dist: black>=23.0.0; extra == "dev"
Requires-Dist: mypy>=1.5.0; extra == "dev"
Requires-Dist: pre-commit>=3.4.0; extra == "dev"
Requires-Dist: build>=1.0.0; extra == "dev"
Requires-Dist: twine>=4.0.0; extra == "dev"
Provides-Extra: mcp
Requires-Dist: mcp>=0.1.0; extra == "mcp"
Requires-Dist: pydantic>=2.0.0; extra == "mcp"
Provides-Extra: watch
Requires-Dist: watchdog>=3.0.0; extra == "watch"
Provides-Extra: all
Requires-Dist: watchdog>=3.0.0; extra == "all"
Requires-Dist: mcp>=0.1.0; extra == "all"
Requires-Dist: pydantic>=2.0.0; extra == "all"
Dynamic: license-file
